odoo/addons/loyalty_limit/README.rst
odoo/addons/loyalty_limit/__init__.py
odoo/addons/loyalty_limit/__manifest__.py
odoo/addons/loyalty_limit/i18n/es.po
odoo/addons/loyalty_limit/i18n/it.po
odoo/addons/loyalty_limit/i18n/loyalty_limit.pot
odoo/addons/loyalty_limit/models/__init__.py
odoo/addons/loyalty_limit/models/loyalty_program.py
odoo/addons/loyalty_limit/readme/CONTRIBUTORS.md
odoo/addons/loyalty_limit/readme/DESCRIPTION.md
odoo/addons/loyalty_limit/security/ir.model.access.csv
odoo/addons/loyalty_limit/static/description/icon.png
odoo/addons/loyalty_limit/static/description/icon.svg
odoo/addons/loyalty_limit/static/description/index.html
odoo/addons/loyalty_limit/tests/__init__.py
odoo/addons/loyalty_limit/tests/test_loyalty_limit.py
odoo/addons/loyalty_limit/views/loyalty_program_views.xml
odoo_addon_loyalty_limit-18.0.1.0.0.2.dist-info/METADATA
odoo_addon_loyalty_limit-18.0.1.0.0.2.dist-info/WHEEL
odoo_addon_loyalty_limit-18.0.1.0.0.2.dist-info/top_level.txt
odoo_addon_loyalty_limit-18.0.1.0.0.2.dist-info/RECORD
